cookiecutter_dinkin_flicka/__init__.py
cookiecutter_dinkin_flicka/__main__.py
cookiecutter_dinkin_flicka/cookiecutter_dinkin_flicka.py
cookiecutter_dinkin_flicka/py.typed
cookiecutter_dinkin_flicka-0.1.0.dist-info/LICENSE
cookiecutter_dinkin_flicka-0.1.0.dist-info/METADATA
cookiecutter_dinkin_flicka-0.1.0.dist-info/WHEEL
cookiecutter_dinkin_flicka-0.1.0.dist-info/entry_points.txt
cookiecutter_dinkin_flicka-0.1.0.dist-info/RECORD
