Metadata-Version: 2.1
Name: cookiecutter-dinkin-flicka
Version: 0.1.0
Summary: Dinkin Flicka: a versatile cookiecutter template for python projects
Home-page: https://github.com/luizdesuo/cookiecutter-dinkin-flicka
License: MIT
Author: Luiz Desuó N.
Author-email: luizdesuo@gmail.com
Requires-Python: >=3.11,<4.0
Classifier: Development Status :: 3 - Alpha
Classifier: License :: OSI Approved :: MIT License
Classifier: Programming Language :: Python :: 3
Classifier: Programming Language :: Python :: 3.11
Classifier: Programming Language :: Python :: 3.12
Requires-Dist: click (>=8.1.7)
Project-URL: Changelog, https://github.com/luizdesuo/cookiecutter-dinkin-flicka/releases
Project-URL: Repository, https://github.com/luizdesuo/cookiecutter-dinkin-flicka
